{
  "generators": {
    "update-markdown-renderer-feature": {
      "version": "1.5.0-beta.1",
      "description": "Update withMarkdownRenderer feature with withPrismHighlighter",
      "implementation": "./src/migrations/update-markdown-renderer-feature/update-markdown-renderer-feature"
    }
  },
  "schematics": {
    "update-markdown-renderer-feature": {
      "version": "1.5.0-beta.1",
      "description": "Update withMarkdownRenderer feature with withPrismHighlighter",
      "factory": "./src/migrations/update-markdown-renderer-feature/compat"
    }
  },
  "packageJsonUpdates": {
    "0.2.0-beta.23": {
      "version": "0.2.0-beta.19",
      "description": "Adds the new peer dependencies for marked to work properly with version 5.0.0",
      "requires": {
        "marked": ">=5.0.0"
      },
      "packages": {
        "marked-gfm-heading-id": {
          "version": "^3.0.4",
          "alwaysAddToPackageJson": true
        },
        "marked-highlight": {
          "version": "^2.0.1",
          "alwaysAddToPackageJson": true
        }
      }
    },
    "0.2.0-beta.26": {
      "version": "0.2.0-beta.25",
      "description": "Adds the new peer dependencies for mermaid",
      "packages": {
        "mermaid": {
          "version": "^10.2.4",
          "alwaysAddToPackageJson": true
        }
      }
    },
    "0.2.8": {
      "version": "0.2.7",
      "description": "Updates marked-gfm-heading-id to support TOCs generation",
      "packages": {
        "marked-gfm-heading-id": {
          "version": "^3.1.0",
          "alwaysAddToPackageJson": true
        }
      }
    },
    "1.5.0-beta.1": {
      "version": "1.4.0",
      "description": "Adds marked-mangle dependency for deprecated marked feature",
      "packages": {
        "marked-mangle": {
          "version": "^1.1.7",
          "alwaysAddToPackageJson": true
        }
      }
    }
  }
}
